{
  "status": "ok",
  "data": {
    "project": "NewBoard",
    "sessionId": "sess-abc123",
    "startedAt": "2026-05-16T15:00:00.000Z",
    "totalTokens": 4500,
    "totalCost": "0.0403",
    "callCount": 5,
    "modelBreakdown": {
      "haiku":  { "calls": 2, "tokens": 1200, "cost": "0.0012" },
      "sonnet": { "calls": 3, "tokens": 3300, "cost": "0.0391" }
    }
  },
  "thresholds": {
    "session": { "used": 4500, "capacity": 44000, "percent": 10.2 },
    "weekly":  { "used": 4500, "capacity": 800000, "percent": 0.6 }
  },
  "alerts": [{
    "level": "ok",
    "message": "You're at 10% of your session budget. Keep working; no restrictions yet."
  }]
}
